top_python_projects/__init__.py
top_python_projects/Calculator/ASCII .py
top_python_projects/Calculator/Mortgage.py
top_python_projects/Calculator/Quadratic_Equation.py
top_python_projects/Calculator/__init__.py
top_python_projects/Calculator/bmi.py
top_python_projects/Calculator/conject.py
top_python_projects/Calculator/grade.py
top_python_projects/Calculator/graph.py
top_python_projects/Calculator/int_diff.py
top_python_projects/Calculator/mega_calculator.py
top_python_projects/Calculator/number_base.py
top_python_projects/Calculator/roman_number.py
top_python_projects/Calculator/sequence.py
top_python_projects/Calculator/special_relativity_calculator.py
top_python_projects/Calculator/stock.py
top_python_projects/Calculator/sudoku.py
top_python_projects/Calculator/time.py
top_python_projects/Calculator/time_calulator.py
top_python_projects/GUI/A_basic_gui_calculator.py
top_python_projects/GUI/Form.py
top_python_projects/GUI/Pikachu.py
top_python_projects/GUI/Quiz.py
top_python_projects/GUI/__init__.py
top_python_projects/GUI/clender.py
top_python_projects/GUI/clock.py
top_python_projects/GUI/doraemon.py
top_python_projects/GUI/file_explorer.py
top_python_projects/GUI/graphics.py
top_python_projects/GUI/happy_birth_day.py
top_python_projects/GUI/notepad.py
top_python_projects/GUI/paint.py
top_python_projects/GUI/rainbow.py
top_python_projects/GUI/search_applications.py
top_python_projects/GUI/snake_ladder.py
top_python_projects/GUI/spelling.py
top_python_projects/GUI/spinner.py
top_python_projects/GUI/tick_cross.py
top_python_projects/GUI/todo.py
top_python_projects/GUI/youtube_download.py
top_python_projects/Game/__init__.py
top_python_projects/Game/blocks.py
top_python_projects/Game/color_guessing.py
top_python_projects/Game/colox.py
top_python_projects/Game/dice.py
top_python_projects/Game/hangman.py
top_python_projects/Game/master_mid.py
top_python_projects/Game/number_details.py
top_python_projects/Game/number_guessing.py
top100_python_projects-0.5.dist-info/LICENSE
top100_python_projects-0.5.dist-info/METADATA
top100_python_projects-0.5.dist-info/WHEEL
top100_python_projects-0.5.dist-info/top_level.txt
top100_python_projects-0.5.dist-info/RECORD
