Metadata-Version: 2.1
Name: top100-python-projects
Version: 0.5
Summary: A collection of Python projects
Author: MRayan Asim
Author-email: mrayanasim09@gmail.com
License-File: LICENSE
